{
    "instance": {
        "magic": "APF_VER_1",
        "variant_select": {
            "id": 666,
            "select": false
        },
        "data_slots": [
            { "id": 1, "filename": "os.bin" },
            { "id": 2, "filename": "gorenuggetsplutonia.ini" },
            { "id": 3, "filename": "doom.elf" },
            { "id": 4, "filename": "PLUTONIA.WAD" },
            { "id": 5, "filename": "dehacked_gibs.wad" },
            { "id": 7, "filename": "bank.ofsf" },
            { "id": 9, "filename": "GorenuggetsPlutonia.cfg" },
            { "id": 10, "filename": "GorenuggetsPlutonia_0.sav" },
            { "id": 11, "filename": "GorenuggetsPlutonia_1.sav" },
            { "id": 12, "filename": "GorenuggetsPlutonia_2.sav" },
            { "id": 13, "filename": "GorenuggetsPlutonia_3.sav" },
            { "id": 14, "filename": "GorenuggetsPlutonia_4.sav" },
            { "id": 15, "filename": "GorenuggetsPlutonia_5.sav" },
            { "id": 16, "filename": "GorenuggetsPlutonia_6.sav" },
            { "id": 17, "filename": "GorenuggetsPlutonia_7.sav" },
            { "id": 18, "filename": "GorenuggetsPlutonia_8.sav" },
            { "id": 19, "filename": "GorenuggetsPlutonia_9.sav" }
        ]
    }
}
